{
  "m_GameObject": {
    "m_FileID": 0,
    "m_PathID": 0
  },
  "m_Enabled": 1,
  "m_Script": {
    "m_FileID": 1,
    "m_PathID": 1397
  },
  "m_Name": "EOTD_TrainingArea_SusieCutOffQueen",
  "Textboxes": {
    "Array": [
      {
        "Character": {
          "Array": [
            {
              "m_FileID": 7,
              "m_PathID": 610
            },
            {
              "m_FileID": 0,
              "m_PathID": 170
            },
            {
              "m_FileID": 6,
              "m_PathID": 231
            },
            {
              "m_FileID": 0,
              "m_PathID": 172
            },
            {
              "m_FileID": 0,
              "m_PathID": 173
            }
          ]
        },
        "Choice": {
          "Array": []
        },
        "Text": {
          "Array": [
            "你踏马说啥呢？！",
            "你能 原谅 我吗",
            "...;行，和平共处，\n别没事挑起战争就行。",
            "我 现在 好 感动@\n都要 哭出来 了",
            "骗你的 xswl\n我 也没 那个 功能 啊"
          ]
        },
        "Action": {
          "Array": [
            {
              "m_FileID": 0,
              "m_PathID": 145
            },
            {
              "m_FileID": 0,
              "m_PathID": 155
            },
            {
              "m_FileID": 0,
              "m_PathID": 162
            },
            {
              "m_FileID": 0,
              "m_PathID": 154
            },
            {
              "m_FileID": 0,
              "m_PathID": 156
            }
          ]
        },
        "Reaction": {
          "Array": []
        },
        "SubActions": {
          "Array": []
        }
      }
    ]
  }
}