{
  "m_GameObject": {
    "m_FileID": 0,
    "m_PathID": 342
  },
  "m_Enabled": 1,
  "m_Script": {
    "m_FileID": 1,
    "m_PathID": 1199
  },
  "m_Name": "",
  "SettingsElementName": "终止",
  "SettingsDescription": "用于返回、退出，\n或立即输出未显示的\n文本。",
  "CurrentlySelected": 0,
  "CanBeCanceled": 0,
  "RawImages_AffectedByColor": {
    "Array": []
  },
  "TMP_AffectedByColor": {
    "Array": [
      {
        "m_FileID": 0,
        "m_PathID": 1391
      },
      {
        "m_FileID": 0,
        "m_PathID": 1346
      }
    ]
  }
}