{
  "m_GameObject": {
    "m_FileID": 0,
    "m_PathID": 0
  },
  "m_Enabled": 1,
  "m_Script": {
    "m_FileID": 1,
    "m_PathID": 1397
  },
  "m_Name": "SupplyCloset_Shelves",
  "Textboxes": {
    "Array": [
      {
        "Character": {
          "Array": [
            {
              "m_FileID": 0,
              "m_PathID": 0
            },
            {
              "m_FileID": 0,
              "m_PathID": 0
            },
            {
              "m_FileID": 0,
              "m_PathID": 0
            }
          ]
        },
        "Choice": {
          "Array": []
        },
        "Text": {
          "Array": [
            "（这是你一路以来冒险\n所得到的战利品。）",
            "（尽管很不情愿，\n但你还是接受了你需要\n归还所有东西的事实。）",
            "（...不然你会被称为\n“本镇著名小偷”的。）"
          ]
        },
        "Action": {
          "Array": []
        },
        "Reaction": {
          "Array": []
        },
        "SubActions": {
          "Array": []
        }
      }
    ]
  }
}