{
  "m_GameObject": {
    "m_FileID": 0,
    "m_PathID": 0
  },
  "m_Enabled": 1,
  "m_Script": {
    "m_FileID": 1,
    "m_PathID": 1397
  },
  "m_Name": "EOTDKrisroom_Manual",
  "Textboxes": {
    "Array": [
      {
        "Character": {
          "Array": [
            {
              "m_FileID": 0,
              "m_PathID": 0
            },
            {
              "m_FileID": 0,
              "m_PathID": 0
            },
            {
              "m_FileID": 5,
              "m_PathID": 234
            }
          ]
        },
        "Choice": {
          "Array": []
        },
        "Text": {
          "Array": [
            "（你的手冊都落灰了。）",
            "（你靠得越近，\n你就越想打噴嚏。）",
            "哈，Kris，\n你也對讀書過敏嗎？"
          ]
        },
        "Action": {
          "Array": []
        },
        "Reaction": {
          "Array": []
        },
        "SubActions": {
          "Array": []
        }
      }
    ]
  }
}